swap/__init__.py
swap/__main__.py
swap/config.py
swap/git.py
swap/lock.py
swap/rsync.py
swap/utils.py
swap/handlers/__init__.py
swap/handlers/add.py
swap/handlers/check.py
swap/handlers/get.py
swap/handlers/init.py
swap/handlers/remove.py
swap/handlers/sync.py
swap/handlers/tree.py
swp-1.0.1.dist-info/METADATA
swp-1.0.1.dist-info/WHEEL
swp-1.0.1.dist-info/entry_points.txt
swp-1.0.1.dist-info/top_level.txt
swp-1.0.1.dist-info/RECORD
