Metadata-Version: 2.1
Name: swp
Version: 1.0.1
Summary: Simple components sharing tool
Home-page: https://github.com/mathix420/swap
Author: Arnaud Gissinger
Author-email: agissing@student.42.fr
License: MIT
Platform: UNKNOWN
Classifier: Intended Audience :: Developers
Classifier: Intended Audience :: System Administrators
Classifier: License :: OSI Approved :: MIT License
Classifier: Programming Language :: Python :: 3 :: Only
Classifier: Programming Language :: Python :: 3.6
Classifier: Programming Language :: Python :: 3.7
Classifier: Programming Language :: Python :: 3.8
Classifier: Programming Language :: Python :: 3.9
Requires-Python: >=3.6
Requires-Dist: setuptools (>=46.0.0)
Requires-Dist: termcolor (>=1.1.0)
Requires-Dist: PyInquirer (>=1.0.3)
Requires-Dist: PyYAML (>=5.4.1)
